setup.py
gifruw/__init__.py
gifruw/parse_ic.py
gifruw.egg-info/PKG-INFO
gifruw.egg-info/SOURCES.txt
gifruw.egg-info/dependency_links.txt
gifruw.egg-info/top_level.txt