Metadata-Version: 1.1
Name: gifruw
Version: 0.1.0
Summary: A tiny, fast HTML templating engine that lets you write your templates in Python.
Home-page: https://github.com/fletom/gifruw
Author: Fletcher Tomalty
Author-email: fletcher@tomalty.com
License: UNKNOWN
Platform: UNKNOWN
Classifier: Programming Language :: Python :: 2
Classifier: Programming Language :: Python :: 2.7
Classifier: Topic :: Internet :: WWW/HTTP :: Dynamic Content
Classifier: Intended Audience :: Developers
Classifier: Environment :: Web Environment
Classifier: Development Status :: 3 - Alpha
